flake8_file_encoding/__init__.py
flake8_file_encoding-0.1.0.dist-info/entry_points.txt
flake8_file_encoding-0.1.0.dist-info/WHEEL
flake8_file_encoding-0.1.0.dist-info/METADATA
flake8_file_encoding-0.1.0.dist-info/RECORD
