Metadata-Version: 2.1
Name: flake8-file-encoding
Version: 0.1.0
Summary: A Flake8 plugin to check for files opened without an explicit encoding
Home-page: https://github.com/rayjolt/flake8-file-encoding
License: MIT
Keywords: flake8,file,open,encoding
Author: Jack Taylor
Author-email: rayjolt@gmail.com
Requires-Python: >=3.4,<4.0
Classifier: Environment :: Console
Classifier: Framework :: Flake8
Classifier: Intended Audience :: Developers
Classifier: License :: OSI Approved :: MIT License
Classifier: Operating System :: OS Independent
Classifier: Programming Language :: Python
Classifier: Programming Language :: Python :: 3
Classifier: Programming Language :: Python :: 3.4
Classifier: Programming Language :: Python :: 3.5
Classifier: Programming Language :: Python :: 3.6
Classifier: Programming Language :: Python :: 3.7
Classifier: Topic :: Software Development :: Libraries :: Python Modules
Classifier: Topic :: Software Development :: Quality Assurance
Requires-Dist: flake8 (>=3,<4)
